{
  "churn_loc_estimate": 72,
  "counts": {
    "assets_added": 2,
    "assets_modified": 2,
    "assets_removed": 0,
    "files_added": 2,
    "files_modified": 5,
    "files_removed": 0,
    "folders_added": 0,
    "folders_modified": 5,
    "folders_removed": 0
  },
  "event_id": "2026-01-07T11:46:47Z",
  "languages": [
    {
      "delta_bytes": 238,
      "estimated_loc_delta": 5,
      "language": "HTML"
    },
    {
      "delta_bytes": -2267,
      "estimated_loc_delta": -67,
      "language": "Python"
    }
  ],
  "net_loc_estimate": -62,
  "schema_version": 1,
  "total_delta_bytes": 744,
  "unknown_delta_bytes": 2773,
  "watch_folders": [
    "Project-20a2de662e"
  ]
}